ml_golem/__init__.py
ml_golem/datatypes.py
ml_golem/model_action.py
ml_golem/model_inference.py
ml_golem/model_trainer.py
ml_golem/base_classes/__init__.py
ml_golem/base_classes/_helper_functions.py
ml_golem/base_classes/_timer.py
ml_golem/base_classes/data_io_object.py
ml_golem/base_classes/dataloading_base.py
ml_golem/base_classes/dataset_base.py
ml_golem/base_classes/loss_base.py
ml_golem/base_classes/model_base.py
ml_golem/base_classes/model_io_base.py
ml_golem/data_transfers/__init__.py
ml_golem/data_transfers/model_copier.py
ml_golem/data_transfers/overleaf_datatypes.py
ml_golem/data_transfers/overleaf_transfer.py
ml_golem/grid_search/__init__.py
ml_golem/grid_search/config_copier.py
ml_golem/grid_search/grid_search_builder.py
ml_golem/grid_search/tensorboard_logic.py
ml_golem/main_loop_logic/__init__.py
ml_golem/main_loop_logic/argparsing.py
ml_golem/main_loop_logic/main_loop.py
ml_golem/main_loop_logic/main_loop_messages.py
ml_golem/main_loop_logic/reserved_keywords.py
ml_golem/model_loading_logic/__init__.py
ml_golem/model_loading_logic/config_based_class.py
ml_golem/model_loading_logic/model_config_keywords.py
ml_golem/overleaf/__init__.py
ml_golem/overleaf/overleaf_datatypes.py
ml_golem/overleaf/overleaf_transfer.py
ml_golem-0.1.10.dist-info/METADATA
ml_golem-0.1.10.dist-info/WHEEL
ml_golem-0.1.10.dist-info/top_level.txt
ml_golem-0.1.10.dist-info/RECORD
